[
  {
    "url": "http://www.epicarmouryunlimited.com/en/2063-larp-archery-gloves",
    "categories": [""],
    "filePath": ""
  },
  {
    "url": "http://www.epicarmouryunlimited.com/en/2064-larp-arrows",
    "categories": [""],
    "filePath": ""
  },
  {
    "url": "http://www.epicarmouryunlimited.com/en/2065-larp-archery-quivers",
    "categories": [""],
    "filePath": ""
  },
  {
    "url": "http://www.epicarmouryunlimited.com/en/2066-larp-bows",
    "categories": [""],
    "filePath": ""
  },
  {
    "url": "http://www.epicarmouryunlimited.com/en/2068-larp-archery-accessories",
    "categories": [""],
    "filePath": ""
  }
]
